{
    "full_name": "Emily McCoy Pixley",
    "birthdate": "August 19, 1904",
    "deathdate": "August 28, 2000",
    "birthplace": "Knoxville, Tennessee",
    "parents": [
        {
            "name": "Mayme McCoy Chandler",
            "birthdate": "ca. 1879",
            "deathdate": null,
            "profession": null
        },
        {
            "name": "David Sanders Chandler",
            "birthdate": "1876",
            "deathdate": null,
            "profession": "District passenger agent with the railroad"
        }
    ],
    "employment": [
        {
            "employer": "Saint Xavier College for Women",
            "job_title": "Instructor and Acting Head of the Mathematics Department",
            "job_year_begin": 1927,
            "job_year_end": 1936,
            "reason_end": "Continued her career at Wayne University"
        },
        {
            "employer": "Wayne University",
            "job_title": "Special Instructor",
            "job_year_begin": 1936,
            "job_year_end": 1949,
            "reason_end": "University anti-nepotism policy"
        },
        {
            "employer": "University of Detroit",
            "job_title": "Assistant Professor, Associate Professor, Professor",
            "job_year_begin": 1948,
            "job_year_end": 1973,
            "reason_end": "Retirement"
        }
    ],
    "degrees": [
        {
            "degree_institution_name": "Randolph-Macon Woman\u2019s College",
            "degree_type": "BA",
            "degree_year": 1926,
            "degree_advisor": null
        },
        {
            "degree_institution_name": "University of Chicago",
            "degree_type": "MS",
            "degree_year": 1927,
            "degree_advisor": "Lawrence Murray Graves"
        },
        {
            "degree_institution_name": "University of Chicago",
            "degree_type": "PhD",
            "degree_year": 1931,
            "degree_advisor": "Leonard Eugene Dickson"
        }
    ],
    "visits": [
        {
            "visit_location": "Alaska",
            "visit_reason": "Travel",
            "visit_year": "Late 1940s"
        },
        {
            "visit_location": "Europe",
            "visit_reason": "Travel",
            "visit_year": "Late 1940s"
        },
        {
            "visit_location": "United States",
            "visit_reason": "Travel",
            "visit_year": "Late 1940s"
        }
    ],
    "honors": [
        {
            "honor_name": "Phi Beta Kappa",
            "honor_year": null
        },
        {
            "honor_name": "Sigma Xi",
            "honor_year": null
        }
    ]
}