{
    "full_name": "Mina Spiegel Rees",
    "birthdate": "August 2, 1902",
    "deathdate": "October 25, 1997",
    "birthplace": "Cleveland, Ohio",
    "parents": [
        {
            "name": "Alice Louise Stackhouse",
            "birthdate": "1870",
            "deathdate": null,
            "profession": null
        },
        {
            "name": "Moses Rees",
            "birthdate": "1858",
            "deathdate": null,
            "profession": null
        }
    ],
    "employment": [
        {
            "employer": "Hunter High School",
            "job_title": "Assistant Teacher",
            "job_year_begin": 1925,
            "job_year_end": null,
            "reason_end": null
        },
        {
            "employer": "Hunter College",
            "job_title": "Instructor of Mathematics",
            "job_year_begin": 1925,
            "job_year_end": 1932,
            "reason_end": "Promoted to Assistant Professor"
        },
        {
            "employer": "Hunter College",
            "job_title": "Assistant Professor",
            "job_year_begin": 1932,
            "job_year_end": 1940,
            "reason_end": "Promoted to Associate Professor"
        },
        {
            "employer": "Hunter College",
            "job_title": "Associate Professor",
            "job_year_begin": 1940,
            "job_year_end": 1943,
            "reason_end": "Leave of absence for Applied Mathematics Panel"
        },
        {
            "employer": "Applied Mathematics Panel, National Defense Research Committee",
            "job_title": "Technical Aide and Executive Assistant",
            "job_year_begin": 1943,
            "job_year_end": 1946,
            "reason_end": "Moved to Office of Naval Research"
        },
        {
            "employer": "Office of Naval Research",
            "job_title": "Head of Mathematics Branch",
            "job_year_begin": 1946,
            "job_year_end": 1949,
            "reason_end": "Promoted to Director of Mathematical Sciences Division"
        },
        {
            "employer": "Office of Naval Research",
            "job_title": "Director of Mathematical Sciences Division",
            "job_year_begin": 1949,
            "job_year_end": 1952,
            "reason_end": "Promoted to Deputy Science Director"
        },
        {
            "employer": "Office of Naval Research",
            "job_title": "Deputy Science Director",
            "job_year_begin": 1952,
            "job_year_end": 1953,
            "reason_end": "Returned to Hunter College"
        },
        {
            "employer": "Hunter College",
            "job_title": "Professor of Mathematics and Dean of the Faculty",
            "job_year_begin": 1953,
            "job_year_end": 1961,
            "reason_end": "City University of New York founded"
        },
        {
            "employer": "City University of New York",
            "job_title": "Professor and Dean of Graduate Studies",
            "job_year_begin": 1961,
            "job_year_end": 1968,
            "reason_end": "Promoted to Provost of Graduate Division"
        },
        {
            "employer": "City University of New York",
            "job_title": "Provost of Graduate Division",
            "job_year_begin": 1968,
            "job_year_end": 1969,
            "reason_end": "Promoted to President of the Graduate School"
        },
        {
            "employer": "City University of New York",
            "job_title": "President of the Graduate School",
            "job_year_begin": 1969,
            "job_year_end": 1972,
            "reason_end": "Retirement"
        }
    ],
    "degrees": [
        {
            "degree_institution_name": "Hunter College",
            "degree_type": "BA",
            "degree_year": 1923,
            "degree_advisor": null
        },
        {
            "degree_institution_name": "Columbia University (Teachers College)",
            "degree_type": "MA",
            "degree_year": 1925,
            "degree_advisor": null
        },
        {
            "degree_institution_name": "University of Chicago",
            "degree_type": "PhD",
            "degree_year": 1931,
            "degree_advisor": "Leonard Eugene Dickson"
        }
    ],
    "visits": [
        {
            "visit_location": "University of Chicago",
            "visit_reason": "Represented Hunter mathematics department at the inauguration of the university\u2019s new president",
            "visit_year": 1929
        },
        {
            "visit_location": "Mexico",
            "visit_reason": "Studied painting",
            "visit_year": null
        },
        {
            "visit_location": "Maine",
            "visit_reason": "Painted during summers",
            "visit_year": null
        },
        {
            "visit_location": "South America",
            "visit_reason": "Travel",
            "visit_year": null
        },
        {
            "visit_location": "Europe",
            "visit_reason": "Travel",
            "visit_year": null
        }
    ],
    "honors": [
        {
            "honor_name": "King\u2019s Medal for Service in the Cause of Freedom",
            "honor_year": 1948
        },
        {
            "honor_name": "President\u2019s Certificate of Merit",
            "honor_year": 1948
        },
        {
            "honor_name": "MAA\u2019s first award for service to mathematics",
            "honor_year": 1962
        },
        {
            "honor_name": "Hunter College High School\u2019s first distinguished graduate",
            "honor_year": 1965
        },
        {
            "honor_name": "AAUW achievement award",
            "honor_year": 1965
        },
        {
            "honor_name": "AAAS Symposium to Honor Mina Rees",
            "honor_year": 1982
        },
        {
            "honor_name": "Public Welfare Medal, National Academy of Sciences",
            "honor_year": 1983
        },
        {
            "honor_name": "IEEE Computer Society Pioneer Award",
            "honor_year": 1989
        }
    ]
}