{
    "full_name": "Helen Gertrude Russell",
    "birthdate": "September 28, 1901",
    "deathdate": "October 24, 1968",
    "birthplace": "Gorham, Maine",
    "parents": [
        {
            "name": "Winifred Parker (Stone)",
            "birthdate": "1869",
            "deathdate": "1970",
            "profession": "Teacher"
        },
        {
            "name": "Walter Earle Russell",
            "birthdate": "1869",
            "deathdate": "1948",
            "profession": "Principal and Faculty Member"
        }
    ],
    "employment": [
        {
            "employer": "Mt. Holly High School",
            "job_title": "Teacher of Mathematics and Latin",
            "job_year_begin": 1921,
            "job_year_end": 1923,
            "reason_end": "Moved to Horace Mann School"
        },
        {
            "employer": "Horace Mann School for Girls",
            "job_title": "Teacher of Mathematics",
            "job_year_begin": 1923,
            "job_year_end": 1927,
            "reason_end": "Pursued graduate work at Radcliffe College"
        },
        {
            "employer": "Wellesley College",
            "job_title": "Instructor",
            "job_year_begin": 1928,
            "job_year_end": 1929,
            "reason_end": "Continued graduate work at Radcliffe College"
        },
        {
            "employer": "Wellesley College",
            "job_title": "Instructor",
            "job_year_begin": 1932,
            "job_year_end": 1936,
            "reason_end": "Promoted to Assistant Professor"
        },
        {
            "employer": "Wellesley College",
            "job_title": "Assistant Professor",
            "job_year_begin": 1936,
            "job_year_end": 1945,
            "reason_end": "Promoted to Associate Professor"
        },
        {
            "employer": "Wellesley College",
            "job_title": "Associate Professor",
            "job_year_begin": 1945,
            "job_year_end": 1951,
            "reason_end": "Promoted to Professor"
        },
        {
            "employer": "Wellesley College",
            "job_title": "Professor",
            "job_year_begin": 1951,
            "job_year_end": 1966,
            "reason_end": "Retired"
        },
        {
            "employer": "Wellesley College",
            "job_title": "Emeritus Professor",
            "job_year_begin": 1966,
            "job_year_end": 1968,
            "reason_end": "Death"
        }
    ],
    "degrees": [
        {
            "degree_institution_name": "Wellesley College",
            "degree_type": "BA",
            "degree_year": 1921,
            "degree_advisor": null
        },
        {
            "degree_institution_name": "Teachers College, Columbia University",
            "degree_type": "MA",
            "degree_year": 1924,
            "degree_advisor": "David Eugene Smith"
        },
        {
            "degree_institution_name": "Radcliffe College",
            "degree_type": "PhD",
            "degree_year": 1932,
            "degree_advisor": "Joseph Leonard Walsh"
        }
    ],
    "visits": [
        {
            "visit_location": "Europe",
            "visit_reason": "Travel",
            "visit_year": 1925
        },
        {
            "visit_location": "Europe",
            "visit_reason": "Travel",
            "visit_year": 1927
        },
        {
            "visit_location": "Western United States",
            "visit_reason": "Travel",
            "visit_year": 1937
        },
        {
            "visit_location": "Western United States",
            "visit_reason": "Travel",
            "visit_year": 1939
        },
        {
            "visit_location": "University of California",
            "visit_reason": "Sabbatical",
            "visit_year": 1942
        },
        {
            "visit_location": "Harvard University",
            "visit_reason": "Sabbatical",
            "visit_year": 1949
        },
        {
            "visit_location": "Harvard University",
            "visit_reason": "Sabbatical",
            "visit_year": 1956
        },
        {
            "visit_location": "Harvard University",
            "visit_reason": "Research Fellow",
            "visit_year": 1963
        },
        {
            "visit_location": "Orient",
            "visit_reason": "Travel",
            "visit_year": 1963
        }
    ],
    "honors": [
        {
            "honor_name": "Phi Beta Kappa",
            "honor_year": null
        },
        {
            "honor_name": "Sigma Xi",
            "honor_year": null
        },
        {
            "honor_name": "AAUP",
            "honor_year": null
        }
    ]
}